{
  "basics": {
    "name": "Hou Huawei",
    "label": "College Student",
    "image": "",
    "email": "houhuawei666@nudt.edu.cn",
    "phone": "",
    "url": "https://houhuawei23.github.io/",
    "summary": "An undergraduate student majoring in computer science and technology at NUDT, with a strong interest in System Software and Distributed System.",

    "profiles": [
      {
        "network": "Twitter",
        "username": "AlbertEinstein",
        "url": "https://twitter.com/AlbertEinstein"
      }
    ]
  },
  "volunteer": [],
  "education": [
    {
      "institution": "National University of Defense Technology",
      "location": "Changsha, China",
      "url": "https://english.nudt.edu.cn/",
      "area": "Computer Science and Technology",
      "studyType": "Bachelor",
      "startDate": "2021-09",
      "endDate": "2025-06",
      "score": "",
      "courses": [
        "Theory of Computaion",
        "Data Structure and Algorithm",
        "Computer Architecture",
        "Compiler Basics",
        "Parallel Compilation Optimization"
      ]
    }
  ],
  "awards": [
    {
      "title": "NUDT Scholarship",
      "date": "2022-09",
      "awarder": "",
      "summary": ""
    },
    {
      "title": "Outstanding Student",
      "date": "2022-09",
      "awarder": "NUDT CS Department",
      "summary": ""
    }
  ],
  "certificates": [],
  "publications": [],
  "skills": [],
  "languages": [
    {
      "language": "Chinese",
      "fluency": "Native speaker"
    },
    {
      "language": "English",
      "fluency": "Fluent"
    }
  ],
  "interests": [],
  "references": [],
  "projects": []
}